docutils_glep/__init__.py
docutils_glep/cli.py
docutils_glep/reader.py
docutils_glep/transforms.py
docutils_glep/html_writer/__init__.py
docutils_glep/html_writer/glep.css
docutils_glep/html_writer/template.txt
docutils_glep-1.5.dist-info/entry_points.txt
docutils_glep-1.5.dist-info/WHEEL
docutils_glep-1.5.dist-info/METADATA
docutils_glep-1.5.dist-info/RECORD
