Metadata-Version: 2.1
Name: docutils-glep
Version: 1.5
Summary: docutils modules & wrapper to process Gentoo Linux Enhancement Proposals
Author: Gentoo Authors
Author-email: Michał Górny <mgorny@gentoo.org>
Requires-Python: >=3.7
Classifier: Development Status :: 5 - Production/Stable
Classifier: Environment :: Console
Classifier: Intended Audience :: Other Audience
Classifier: License :: Public Domain
Classifier: Operating System :: OS Independent
Classifier: Programming Language :: Python
Classifier: Topic :: Documentation
Requires-Dist: docutils
Requires-Dist: PyYAML
Project-URL: Homepage, https://github.com/mgorny/docutils-glep/
